dtt/__init__.py
dtt/colors.py
dtt/config.py
dtt/help.py
dtt/keypad.py
dtt/logger.py
dtt/main.py
dtt/dock/__init__.py
dtt/dock/container.py
dtt/dock/main.py
dtt/kubectl/__init__.py
dtt/kubectl/client.py
dtt/kubectl/main.py
dtt/kubectl/pod.py
test/__init__.py
test/test_container.py
test/test_main.py
dtt-0.9.2.dist-info/LICENSE
dtt-0.9.2.dist-info/METADATA
dtt-0.9.2.dist-info/WHEEL
dtt-0.9.2.dist-info/entry_points.txt
dtt-0.9.2.dist-info/top_level.txt
dtt-0.9.2.dist-info/RECORD
